README.rst
setup.py
python_tlm.egg-info/PKG-INFO
python_tlm.egg-info/SOURCES.txt
python_tlm.egg-info/dependency_links.txt
python_tlm.egg-info/top_level.txt
tlm/__init__.py
tlm/version.py